psims/__init__.py
psims/compression.py
psims/document.py
psims/example.py
psims/utils.py
psims/version.py
psims/xml.py
psims/controlled_vocabulary/__init__.py
psims/controlled_vocabulary/controlled_vocabulary.py
psims/controlled_vocabulary/entity.py
psims/controlled_vocabulary/obo.py
psims/controlled_vocabulary/relationship.py
psims/controlled_vocabulary/resid.py
psims/controlled_vocabulary/type_definition.py
psims/controlled_vocabulary/unimod.py
psims/controlled_vocabulary/vendor/XLMOD.obo.gz
psims/controlled_vocabulary/vendor/__init__.py
psims/controlled_vocabulary/vendor/gno.obo.gz
psims/controlled_vocabulary/vendor/go.obo.gz
psims/controlled_vocabulary/vendor/list_cvs.py
psims/controlled_vocabulary/vendor/pato.obo.gz
psims/controlled_vocabulary/vendor/psi-mod.obo.gz
psims/controlled_vocabulary/vendor/psi-ms.obo.gz
psims/controlled_vocabulary/vendor/record.json
psims/controlled_vocabulary/vendor/unimod_tables.xml.gz
psims/controlled_vocabulary/vendor/unit.obo.gz
psims/controlled_vocabulary/vendor/update_vendored_cvs.py
psims/mzid/__init__.py
psims/mzid/components.py
psims/mzid/utils.py
psims/mzid/writer.py
psims/mzml/__init__.py
psims/mzml/binary_encoding.py
psims/mzml/components.py
psims/mzml/element_builder.py
psims/mzml/index.py
psims/mzml/native_id.py
psims/mzml/utils.py
psims/mzml/writer.py
psims/mzmlb/__init__.py
psims/mzmlb/components.py
psims/mzmlb/writer.py
psims/test/__init__.py
psims/test/mzid_data.py
psims/test/test_cv.py
psims/test/test_document.py
psims/test/test_mzid_writer.py
psims/test/test_mzml_writer.py
psims/test/test_mzmlb_writer.py
psims/test/test_transform_mzid.py
psims/test/test_transform_mzml.py
psims/test/utils.py
psims/test/test_data/__init__.py
psims/transform/__init__.py
psims/transform/mzid.py
psims/transform/mzml.py
psims/transform/utils.py
psims/validation/__init__.py
psims/validation/validator.py
psims/validation/semantic/__init__.py
psims/validation/semantic/rule_definitions.py
psims/validation/semantic/data/__init__.py
psims-1.3.5.dist-info/LICENSE
psims-1.3.5.dist-info/METADATA
psims-1.3.5.dist-info/WHEEL
psims-1.3.5.dist-info/top_level.txt
psims-1.3.5.dist-info/RECORD
