Metadata-Version: 2.2
Name: psims
Version: 1.3.5
Summary: Writers and controlled vocabulary manager for PSI-MS's mzML and mzIdentML standards
Home-page: https://github.com/mobiusklein/psims
Maintainer: Joshua Klein
Maintainer-email: jaklein@bu.edu
Project-URL: Source Code, https://github.com/mobiusklein/psims
Project-URL: Issue Tracker, https://github.com/mobiusklein/psims/issues
Classifier: License :: OSI Approved :: Apache Software License
Classifier: Topic :: Text Processing :: Markup :: XML
Classifier: Intended Audience :: Science/Research
Classifier: Development Status :: 5 - Production/Stable
Classifier: Programming Language :: Python :: 3.8
Classifier: Programming Language :: Python :: 3.9
Classifier: Programming Language :: Python :: 3.10
Requires-Python: >3.8
License-File: LICENSE
Requires-Dist: lxml
Requires-Dist: six
Requires-Dist: sqlalchemy
Requires-Dist: numpy
Provides-Extra: mzmlb
Requires-Dist: h5py; extra == "mzmlb"
Requires-Dist: hdf5plugin; extra == "mzmlb"
Provides-Extra: numpress
Requires-Dist: pynumpress; extra == "numpress"
Provides-Extra: all
Requires-Dist: h5py; extra == "all"
Requires-Dist: hdf5plugin; extra == "all"
Requires-Dist: pynumpress; extra == "all"
Dynamic: classifier
Dynamic: description
Dynamic: description-content-type
Dynamic: home-page
Dynamic: maintainer
Dynamic: maintainer-email
Dynamic: project-url
Dynamic: provides-extra
Dynamic: requires-dist
Dynamic: requires-python
Dynamic: summary
